INSTALL
LICENSE
MANIFEST.in
README
README.rst
setup.py
bin/odpstyles
bin/otptweak
bin/rst2odp
odplib/__init__.py
odplib/imagescale.py
odplib/meta.py
odplib/preso.py
odplib/zipwrap.py
odplib/data/auto_list.xml
odplib/data/number_list.xml
odplib/data/settings.xml
odplib/data/styles.xml
rst2odp.egg-info/PKG-INFO
rst2odp.egg-info/SOURCES.txt
rst2odp.egg-info/dependency_links.txt
rst2odp.egg-info/pbr.json
rst2odp.egg-info/requires.txt
rst2odp.egg-info/top_level.txt