Metadata-Version: 1.1
Name: rst2odp
Version: 0.3.1
Summary: Converter for rst to OpenOffice Impress
Home-page: https://github.com/mattharrison/rst2odp
Author: matt harrison
Author-email: matthewharrison@gmail.com
License: Apache
Platform: UNKNOWN
Classifier: Development Status :: 4 - Beta
Classifier: Environment :: Console
Classifier: Intended Audience :: End Users/Desktop
Classifier: Intended Audience :: Developers
Classifier: Operating System :: MacOS :: MacOS X
Classifier: Operating System :: Microsoft :: Windows
Classifier: Operating System :: POSIX
Classifier: Programming Language :: Python
Classifier: Topic :: Office/Business
